{
  "schema": "lastlight.fixture-goldens.v1",
  "schemaVersion": 1,
  "balance": {
    "version": "2026.07.13-mastery.1",
    "hash": "fnv1a32:f9f93ac0"
  },
  "replay": {
    "schema": "lastlight.replay.v12",
    "stepHz": 60,
    "rng": "xoshiro128ss-v1"
  },
  "fixtures": [
    {
      "id": "early-solo-contact",
      "seed": "10000000000000000000000000000001",
      "hashes": [
        {
          "tick": 0,
          "hash": "41608ebfd67ce19e"
        },
        {
          "tick": 60,
          "hash": "2f641bda06ad10b4"
        },
        {
          "tick": 120,
          "hash": "e19aec467b84d9a4"
        },
        {
          "tick": 180,
          "hash": "53415cbb849619ad"
        }
      ],
      "summary": {
        "stage": "running",
        "tick": 900,
        "wave": 0,
        "level": 1,
        "kills": 1,
        "gold": 0,
        "teamXP": 0,
        "bossPhase": 1,
        "entities": {
          "players": 1,
          "drones": 0,
          "enemies": 31,
          "projectiles": 3,
          "hostile": 0,
          "effects": 0,
          "orbs": 1,
          "drops": 0,
          "pods": 14,
          "objectives": 0,
          "relayBalls": 0,
          "feathers": 0,
          "tasks": 0
        },
        "players": [
          {
            "slot": 0,
            "specialist": "zuri",
            "hp": 10,
            "damage": 94.7,
            "kills": 1,
            "revives": 0,
            "downed": false,
            "dead": false
          }
        ]
      },
      "baselineMetrics": {
        "maxSnapshotBytes": 17592,
        "maxTotalEntities": 50,
        "maxWorkUnitsPerTick": 167
      }
    },
    {
      "id": "mid-solo-build",
      "seed": "20000000000000000000000000000002",
      "hashes": [
        {
          "tick": 0,
          "hash": "7d969605b61ec323"
        },
        {
          "tick": 60,
          "hash": "db6d9d6cd06248ab"
        },
        {
          "tick": 120,
          "hash": "77ab21039652a180"
        },
        {
          "tick": 180,
          "hash": "915d138c92eb252c"
        },
        {
          "tick": 240,
          "hash": "d17520d451bfe6a4"
        },
        {
          "tick": 300,
          "hash": "12117224f3e0bca3"
        }
      ],
      "summary": {
        "stage": "running",
        "tick": 6900,
        "wave": 3,
        "level": 8,
        "kills": 22,
        "gold": 0,
        "teamXP": 27,
        "bossPhase": 1,
        "entities": {
          "players": 1,
          "drones": 1,
          "enemies": 69,
          "projectiles": 24,
          "hostile": 11,
          "effects": 1,
          "orbs": 18,
          "drops": 4,
          "pods": 10,
          "objectives": 0,
          "relayBalls": 0,
          "feathers": 0,
          "tasks": 2
        },
        "players": [
          {
            "slot": 0,
            "specialist": "echo",
            "hp": 10,
            "damage": 9046.7,
            "kills": 22,
            "revives": 0,
            "downed": false,
            "dead": false
          }
        ]
      },
      "baselineMetrics": {
        "maxSnapshotBytes": 47184,
        "maxTotalEntities": 151,
        "maxWorkUnitsPerTick": 2715
      }
    },
    {
      "id": "late-solo-storm",
      "seed": "30000000000000000000000000000003",
      "hashes": [
        {
          "tick": 0,
          "hash": "cbc90b59d27a4cee"
        },
        {
          "tick": 30,
          "hash": "dde3ab1333d55813"
        },
        {
          "tick": 60,
          "hash": "8b314974e1505502"
        },
        {
          "tick": 90,
          "hash": "e7639c91c6c32828"
        },
        {
          "tick": 120,
          "hash": "9737fdd944889399"
        }
      ],
      "summary": {
        "stage": "running",
        "tick": 13020,
        "wave": 6,
        "level": 14,
        "kills": 0,
        "gold": 0,
        "teamXP": 0,
        "bossPhase": 1,
        "entities": {
          "players": 1,
          "drones": 1,
          "enemies": 170,
          "projectiles": 202,
          "hostile": 122,
          "effects": 206,
          "orbs": 500,
          "drops": 1,
          "pods": 13,
          "objectives": 0,
          "relayBalls": 0,
          "feathers": 0,
          "tasks": 0
        },
        "players": [
          {
            "slot": 0,
            "specialist": "gale",
            "hp": 9.5,
            "damage": 18212.3,
            "kills": 0,
            "revives": 0,
            "downed": false,
            "dead": false
          }
        ]
      },
      "baselineMetrics": {
        "maxSnapshotBytes": 201520,
        "maxTotalEntities": 1229,
        "maxWorkUnitsPerTick": 41190
      }
    },
    {
      "id": "objective-coordination",
      "seed": "40000000000000000000000000000004",
      "hashes": [
        {
          "tick": 0,
          "hash": "9e2265b373c3f2cb"
        },
        {
          "tick": 30,
          "hash": "de92655e02cbcb37"
        },
        {
          "tick": 60,
          "hash": "391bda8f5226ab89"
        },
        {
          "tick": 90,
          "hash": "ab58ce927de14231"
        },
        {
          "tick": 120,
          "hash": "195e42f2806fc241"
        },
        {
          "tick": 150,
          "hash": "18734dcc8aa2e405"
        },
        {
          "tick": 180,
          "hash": "27076b8d7a46ac6e"
        },
        {
          "tick": 210,
          "hash": "b11012fb753af302"
        }
      ],
      "summary": {
        "stage": "running",
        "tick": 4410,
        "wave": 2,
        "level": 5,
        "kills": 0,
        "gold": 70,
        "teamXP": 38.4,
        "bossPhase": 1,
        "entities": {
          "players": 2,
          "drones": 0,
          "enemies": 24,
          "projectiles": 0,
          "hostile": 0,
          "effects": 0,
          "orbs": 0,
          "drops": 1,
          "pods": 14,
          "objectives": 0,
          "relayBalls": 0,
          "feathers": 0,
          "tasks": 0
        },
        "players": [
          {
            "slot": 0,
            "specialist": "sola",
            "hp": 11,
            "damage": 445.5,
            "kills": 0,
            "revives": 0,
            "downed": false,
            "dead": false
          },
          {
            "slot": 1,
            "specialist": "bront",
            "hp": 15,
            "damage": 284,
            "kills": 0,
            "revives": 0,
            "downed": false,
            "dead": false
          }
        ]
      },
      "baselineMetrics": {
        "maxSnapshotBytes": 18867,
        "maxTotalEntities": 43,
        "maxWorkUnitsPerTick": 136
      }
    },
    {
      "id": "multiplayer-four-player",
      "seed": "50000000000000000000000000000005",
      "hashes": [
        {
          "tick": 0,
          "hash": "5876353f6cac0a27"
        },
        {
          "tick": 60,
          "hash": "2ecdc70ce0315098"
        },
        {
          "tick": 120,
          "hash": "52e508cbe128ea47"
        },
        {
          "tick": 180,
          "hash": "bbc773bd275664ef"
        },
        {
          "tick": 240,
          "hash": "ff3582da24731add"
        }
      ],
      "summary": {
        "stage": "running",
        "tick": 8640,
        "wave": 4,
        "level": 10,
        "kills": 38,
        "gold": 40,
        "teamXP": 12,
        "bossPhase": 1,
        "entities": {
          "players": 4,
          "drones": 1,
          "enemies": 100,
          "projectiles": 10,
          "hostile": 34,
          "effects": 166,
          "orbs": 30,
          "drops": 11,
          "pods": 5,
          "objectives": 0,
          "relayBalls": 0,
          "feathers": 0,
          "tasks": 1
        },
        "players": [
          {
            "slot": 0,
            "specialist": "zuri",
            "hp": 10,
            "damage": 70374.3,
            "kills": 37,
            "revives": 0,
            "downed": false,
            "dead": false
          },
          {
            "slot": 1,
            "specialist": "echo",
            "hp": 10,
            "damage": 12608.8,
            "kills": 1,
            "revives": 1,
            "downed": false,
            "dead": false
          },
          {
            "slot": 2,
            "specialist": "sola",
            "hp": 11,
            "damage": 1456,
            "kills": 0,
            "revives": 0,
            "downed": false,
            "dead": false
          },
          {
            "slot": 3,
            "specialist": "bront",
            "hp": 7.5,
            "damage": 3660,
            "kills": 0,
            "revives": 0,
            "downed": false,
            "dead": false
          }
        ]
      },
      "baselineMetrics": {
        "maxSnapshotBytes": 101815,
        "maxTotalEntities": 363,
        "maxWorkUnitsPerTick": 16646
      }
    },
    {
      "id": "apex-beachhead",
      "seed": "60000000000000000000000000000006",
      "hashes": [
        {
          "tick": 0,
          "hash": "21e2ee5a0c38c8f1"
        },
        {
          "tick": 30,
          "hash": "eef647eb79e14561"
        },
        {
          "tick": 60,
          "hash": "5225755cea39962c"
        },
        {
          "tick": 90,
          "hash": "73cb58e9dd83ca18"
        },
        {
          "tick": 120,
          "hash": "ce14c682ad2ee3ec"
        },
        {
          "tick": 150,
          "hash": "7a716e41361cdbd5"
        },
        {
          "tick": 180,
          "hash": "1870a4411704666d"
        }
      ],
      "summary": {
        "stage": "boss",
        "tick": 14580,
        "wave": 6,
        "level": 16,
        "kills": 0,
        "gold": 0,
        "teamXP": 0,
        "bossPhase": 2,
        "entities": {
          "players": 2,
          "drones": 1,
          "enemies": 1,
          "projectiles": 17,
          "hostile": 0,
          "effects": 4,
          "orbs": 0,
          "drops": 4,
          "pods": 10,
          "objectives": 0,
          "relayBalls": 0,
          "feathers": 0,
          "tasks": 0
        },
        "players": [
          {
            "slot": 0,
            "specialist": "rift",
            "hp": 10,
            "damage": 3755.4,
            "kills": 0,
            "revives": 0,
            "downed": false,
            "dead": false
          },
          {
            "slot": 1,
            "specialist": "nova",
            "hp": 9,
            "damage": 1514.5,
            "kills": 0,
            "revives": 0,
            "downed": false,
            "dead": false
          }
        ]
      },
      "baselineMetrics": {
        "maxSnapshotBytes": 17775,
        "maxTotalEntities": 40,
        "maxWorkUnitsPerTick": 241
      }
    },
    {
      "id": "stress-entity-ceiling",
      "seed": "70000000000000000000000000000007",
      "hashes": [
        {
          "tick": 0,
          "hash": "9cef1994a0be8861"
        },
        {
          "tick": 15,
          "hash": "7f483b82d0799503"
        },
        {
          "tick": 30,
          "hash": "d454daaf93af6d76"
        },
        {
          "tick": 45,
          "hash": "22e32577aac74dcb"
        },
        {
          "tick": 60,
          "hash": "7d03c64176c36e7b"
        }
      ],
      "summary": {
        "stage": "running",
        "tick": 13260,
        "wave": 6,
        "level": 18,
        "kills": 0,
        "gold": 0,
        "teamXP": 0,
        "bossPhase": 1,
        "entities": {
          "players": 1,
          "drones": 1,
          "enemies": 300,
          "projectiles": 618,
          "hostile": 343,
          "effects": 260,
          "orbs": 1000,
          "drops": 2,
          "pods": 12,
          "objectives": 0,
          "relayBalls": 0,
          "feathers": 0,
          "tasks": 0
        },
        "players": [
          {
            "slot": 0,
            "specialist": "vesper",
            "hp": 9.5,
            "damage": 24498.3,
            "kills": 0,
            "revives": 0,
            "downed": false,
            "dead": false
          }
        ]
      },
      "baselineMetrics": {
        "maxSnapshotBytes": 406867,
        "maxTotalEntities": 2556,
        "maxWorkUnitsPerTick": 216989
      }
    }
  ]
}
